connector/__init__.py
connector/my_awesome_connector.py
connector/my_csv_connector.py
custom_connector-0.0.2.dist-info/METADATA
custom_connector-0.0.2.dist-info/WHEEL
custom_connector-0.0.2.dist-info/top_level.txt
custom_connector-0.0.2.dist-info/RECORD
