Metadata-Version: 2.1
Name: custom-connector
Version: 0.0.2
Summary: Ingestion Framework for OpenMetadata
Home-page: https://open-metadata.org/
Author: OpenMetadata Committers
License: Apache License 2.0
Requires-Python: >=3.7
Requires-Dist: openmetadata-ingestion (~=1.1.2)
